pyxyfy/__init__.py
pyxyfy/__main__.py
pyxyfy/logger.py
pyxyfy/scratch_session_config.py
pyxyfy/session.py
pyxyfy/calibration/charuco.py
pyxyfy/calibration/corner_tracker.py
pyxyfy/calibration/draw_charuco.py
pyxyfy/calibration/monocalibrator.py
pyxyfy/calibration/omnicalibrator.py
pyxyfy/calibration/capture_volume/capture_volume.py
pyxyfy/calibration/capture_volume/capture_volume_stage_1.pkl
pyxyfy/calibration/capture_volume/point_estimates.py
pyxyfy/calibration/capture_volume/quality_controller.py
pyxyfy/calibration/capture_volume/seaborn_summaries.py
pyxyfy/calibration/capture_volume/helper_functions/get_point_estimates.py
pyxyfy/calibration/capture_volume/helper_functions/get_stereotriangulated_table.py
pyxyfy/cameras/camera.py
pyxyfy/cameras/camera_array.py
pyxyfy/cameras/camera_array_builder.py
pyxyfy/cameras/data_packets.py
pyxyfy/cameras/live_stream.py
pyxyfy/cameras/pyav_sandbox.py
pyxyfy/cameras/synchronizer.py
pyxyfy/gui/main.py
pyxyfy/gui/qt_logger.py
pyxyfy/gui/widgets.py
pyxyfy/gui/wizard_charuco.py
pyxyfy/gui/wizard_directory.py
pyxyfy/gui/camera_config/camera_config_dialogue.py
pyxyfy/gui/camera_config/camera_config_dialogue_old.py
pyxyfy/gui/camera_config/camera_tabs.py
pyxyfy/gui/camera_config/frame_emitter.py
pyxyfy/gui/icons/orb.svg
pyxyfy/gui/icons/rotate-camera-left.svg
pyxyfy/gui/icons/rotate-camera-right.svg
pyxyfy/gui/icons/rotate_right.svg
pyxyfy/gui/omniframe/omni_frame_builder.py
pyxyfy/gui/omniframe/omni_frame_widget.py
pyxyfy/gui/vizualize/camera_mesh.py
pyxyfy/gui/vizualize/capture_volume_dialog.py
pyxyfy/gui/vizualize/capture_volume_visualizer.py
pyxyfy/recording/recorded_stream.py
pyxyfy/recording/undistort_video.py
pyxyfy/recording/video_recorder.py
pyxyfy/triangulate/stereo_points_builder.py
pyxyfy/triangulate/triangulator.py
pyxyfy-0.0.0.dist-info/entry_points.txt
pyxyfy-0.0.0.dist-info/LICENSE.md
pyxyfy-0.0.0.dist-info/WHEEL
pyxyfy-0.0.0.dist-info/METADATA
pyxyfy-0.0.0.dist-info/RECORD
