Metadata-Version: 2.1
Name: pyxyfy
Version: 0.0.0
Summary: GUI tool for calibrating motion capture systems composed of multiple standard webcams
Keywords: opencv,tracking,calibration,python,webcam
Author-email: Mac Prible <prible@gmail.com>
Requires-Python: >=3.8
Classifier: License :: OSI Approved :: GNU Affero General Public License v3 or later (AGPLv3+)
Classifier: Programming Language :: Python
Classifier: Programming Language :: Python :: 3
Requires-Dist: numpy==1.23.3
Requires-Dist: opencv-contrib-python==4.6.0.66
Requires-Dist: pyqt6==6.4.0
Requires-Dist: scipy==1.9.2
Requires-Dist: pandas==1.5.2
Requires-Dist: pyqtgraph==0.13.1
Requires-Dist: pyopengl
Requires-Dist: toml
Requires-Dist: seaborn
Requires-Dist: black ; extra == "dev"
Requires-Dist: bumpver ; extra == "dev"
Requires-Dist: isort ; extra == "dev"
Requires-Dist: pip-tools ; extra == "dev"
Requires-Dist: pytest ; extra == "dev"
Provides-Extra: dev
